sendsmtp/__init__.py
sendsmtp/__main__.py
sendsmtp/cli.py
sendsmtp/sender.py
sendsmtp-1.0.0.dist-info/entry_points.txt
sendsmtp-1.0.0.dist-info/LICENSE
sendsmtp-1.0.0.dist-info/WHEEL
sendsmtp-1.0.0.dist-info/METADATA
sendsmtp-1.0.0.dist-info/RECORD
