Metadata-Version: 2.1
Name: sendsmtp
Version: 1.0.0
Summary: CLI SMTP client in pure Python
Home-page: https://github.com/TitaniumHocker/sendsmtp
License: MIT
Keywords: smtp,cli
Author: Ivan Fedorov
Author-email: inbox@titaniumhocker.ru
Requires-Python: >=3.6,<4.0
Classifier: Development Status :: 4 - Beta
Classifier: Environment :: Console
Classifier: License :: OSI Approved :: MIT License
Classifier: Operating System :: POSIX :: Linux
Classifier: Programming Language :: Python
Classifier: Programming Language :: Python :: 3
Classifier: Programming Language :: Python :: 3.10
Classifier: Programming Language :: Python :: 3.6
Classifier: Programming Language :: Python :: 3.7
Classifier: Programming Language :: Python :: 3.8
Classifier: Programming Language :: Python :: 3.9
Classifier: Topic :: Communications :: Email
Classifier: Topic :: Communications :: Email :: Email Clients (MUA)
Project-URL: Bug Tracker, https://github.com/TitaniumHocker/sendsmtp/issues
